Metadata-Version: 1.1
Name: drf-fields-permissions
Version: 0.1.0
Summary: Permissions for django-rest fields
Home-page: https://github.com/starnavi-team/django_rest_fields_permissions
Author: Andrii Pidlisnyi
Author-email: andrii.pidlisnyi@gmail.com
License: BSD
Platform: UNKNOWN
Classifier: Development Status :: 2 - Pre-Alpha
Classifier: Environment :: Web Environment
Classifier: Framework :: Django
Classifier: Intended Audience :: Developers
Classifier: License :: OSI Approved :: BSD License
Classifier: Operating System :: OS Independent
Classifier: Natural Language :: English
Classifier: Programming Language :: Python :: 3.5
Classifier: Programming Language :: Python :: 3.6
Classifier: Topic :: Internet :: WWW/HTTP
